tcgplayer/__init__.py
tcgplayer/types/__init__.py
tcgplayer-0.1.0.dist-info/LICENSE
tcgplayer-0.1.0.dist-info/METADATA
tcgplayer-0.1.0.dist-info/WHEEL
tcgplayer-0.1.0.dist-info/RECORD
