Metadata-Version: 2.1
Name: tcgplayer
Version: 0.1.0
Summary: Python SDK for the TCG Player API
Home-page: https://github.com/ThatDevShparki/tcgplayer
License: MIT
Author: ThatDevShparki
Author-email: shparki@thatdev.io
Requires-Python: >=3.9,<4.0
Classifier: License :: OSI Approved :: MIT License
Classifier: Programming Language :: Python :: 3
Classifier: Programming Language :: Python :: 3.9
Classifier: Programming Language :: Python :: 3.10
Classifier: Programming Language :: Python :: 3.11
Classifier: Programming Language :: Python :: 3.12
Classifier: Programming Language :: Python :: 3.13
Project-URL: Repository, https://github.com/ThatDevShparki/tcgplayer
